nfa_plugin_software_enumeration/__init__.py
nfa_plugin_software_enumeration/software_enumeration.py
nfa_plugin_software_enumeration-0.1.2.dist-info/licenses/LICENSE
nfa_plugin_software_enumeration-0.1.2.dist-info/METADATA
nfa_plugin_software_enumeration-0.1.2.dist-info/WHEEL
nfa_plugin_software_enumeration-0.1.2.dist-info/entry_points.txt
nfa_plugin_software_enumeration-0.1.2.dist-info/top_level.txt
nfa_plugin_software_enumeration-0.1.2.dist-info/RECORD
