Metadata-Version: 2.4
Name: nfa-plugin-software-enumeration
Version: 0.1.2
Summary: Software Enumeration report plugin for LimberDuck NFA (nessus file analyzer)
Home-page: https://limberduck.org/en/latest/tools/nessus-file-analyzer/advanced-reports/software-enumeration/
Author: Damian Krawczyk
Author-email: damian.krawczyk@limberduck.org
Classifier: Programming Language :: Python :: 3.13
Classifier: Programming Language :: Python :: 3.12
Classifier: Programming Language :: Python :: 3.11
Classifier: Programming Language :: Python :: 3.10
Classifier: License :: OSI Approved :: GNU General Public License v3 (GPLv3)
Classifier: Operating System :: OS Independent
Classifier: Development Status :: 4 - Beta
Requires-Python: >=3.10
License-File: LICENSE
Requires-Dist: nessus-file-analyzer>=0.12.0
Dynamic: author
Dynamic: author-email
Dynamic: classifier
Dynamic: description
Dynamic: description-content-type
Dynamic: home-page
Dynamic: license-file
Dynamic: requires-dist
Dynamic: requires-python
Dynamic: summary
